{
  "entityType" : "NOTIFICATION_RULE",
  "entity" : {
    "additionalConfig" : {
      "description" : "Send notification to tenant admins when comment is added by user on active alarm"
    },
    "enabled" : true,
    "externalId" : null,
    "id" : {
      "entityType" : "NOTIFICATION_RULE",
      "id" : "1a8f7db0-77ed-11ee-92d7-c9d101394cdd"
    },
    "name" : "Comment on active alarm",
    "recipientsConfig" : {
      "targets" : [ "1a8a4d90-77ed-11ee-92d7-c9d101394cdd" ],
      "triggerType" : "ALARM_COMMENT"
    },
    "templateId" : {
      "entityType" : "NOTIFICATION_TEMPLATE",
      "id" : "1a8f2f90-77ed-11ee-92d7-c9d101394cdd"
    },
    "triggerConfig" : {
      "triggerType" : "ALARM_COMMENT",
      "alarmSeverities" : null,
      "alarmStatuses" : [ "ACTIVE" ],
      "alarmTypes" : null,
      "notifyOnCommentUpdate" : false,
      "onlyUserComments" : true,
      "triggerType" : "ALARM_COMMENT"
    },
    "triggerType" : "ALARM_COMMENT"
  },
  "relations" : [ ],
  "attributes" : {
    "SERVER_SCOPE" : [ ]
  }
}